gemimg/__init__.py
gemimg/__main__.py
gemimg/gemimg.py
gemimg/grid.py
gemimg/utils.py
gemimg-0.4.0.dist-info/licenses/LICENSE
gemimg-0.4.0.dist-info/METADATA
gemimg-0.4.0.dist-info/WHEEL
gemimg-0.4.0.dist-info/entry_points.txt
gemimg-0.4.0.dist-info/top_level.txt
gemimg-0.4.0.dist-info/RECORD
