Metadata-Version: 2.4
Name: gemimg
Version: 0.4.0
Summary: Lightweight wrapper for generating and editing images from Nano Banana / Gemini 2.5 Flash Image.
Author-email: Max Woolf <max@minimaxir.com>
License-Expression: MIT
Project-URL: Homepage, https://github.com/minimaxir/gemimg
Keywords: gemini,nano-banana,image generation,ai
Requires-Python: >=3.10
License-File: LICENSE
Requires-Dist: httpx>=0.28.1
Requires-Dist: python-dotenv>=1.1.1
Requires-Dist: orjson>=3.11.3
Requires-Dist: Pillow>=11.3.0
Dynamic: license-file
